Metadata-Version: 1.1
Name: kombu-encrypted-serializer
Version: 0.1.0
Summary: Kombu encrypted serializer
Home-page: https://github.com/roverdotcom/kombu-encrypted-serializer
Author: Bryan Shelton
Author-email: bryan@rover.com
License: MIT
Keywords: kombu_encrypted_serializer
Platform: UNKNOWN
Classifier: Intended Audience :: Developers
Classifier: License :: OSI Approved :: MIT License
Classifier: Natural Language :: English
